Metadata-Version: 2.1
Name: ossconer
Version: 0.0.4
Summary: Python交互OSS，更方便地使用一些常用功能
Author: WangTuo
Author-email: markadc@126.com
License: MIT
Keywords: Python,OSS
